{"nome":"Cliente","musicas":[{"song":"Acceptable in the 80\u0027s","artist":"Calvin Harris","duration_ms":333680,"genre":"hip hop, pop, Dance/Electronic","year":"2007","popularity":"57","key":7,"Tonalidade":"G"},{"song":"Come on over Baby (All I Want Is You) - Radio Version","artist":"Christina Aguilera","duration_ms":203333,"genre":"pop","year":"1999","popularity":"64","key":8,"Tonalidade":"Ab"},{"song":"It Will Rain","artist":"Bruno Mars","duration_ms":257720,"genre":"pop","year":"2011","popularity":"74","key":2,"Tonalidade":"D"},{"song":"More Than You Know","artist":"Axwell /\\ Ingrosso","duration_ms":203000,"genre":"pop, Dance/Electronic","year":"2017","popularity":"0","key":5,"Tonalidade":"F"},{"song":"Thunder in My Heart Again (Radio Edit)","artist":"Meck","duration_ms":189800,"genre":"set()","year":"2005","popularity":"46","key":2,"Tonalidade":"D"}]}